MANIFEST.in
README.md
setup.py
django_caldav/__init__.py
django_caldav/__init__.pyc
django_caldav/acl.py
django_caldav/acl.pyc
django_caldav/lock.py
django_caldav/lock.pyc
django_caldav/models.py
django_caldav/models.pyc
django_caldav/resources.py
django_caldav/resources.pyc
django_caldav/utils.py
django_caldav/utils.pyc
django_caldav/views.py
django_caldav/views.pyc
django_caldav.egg-info/PKG-INFO
django_caldav.egg-info/SOURCES.txt
django_caldav.egg-info/dependency_links.txt
django_caldav.egg-info/not-zip-safe
django_caldav.egg-info/requires.txt
django_caldav.egg-info/top_level.txt
django_caldav/templates/django_caldav/index.html