Metadata-Version: 1.1
Name: django-caldav
Version: 0.5
Summary: CalDAV implementation for Django offering Feed interface
Home-page: http://www.wpj.cz
Author: Petr Knap
Author-email: knap@wpj.cz
License: UNKNOWN
Platform: UNKNOWN
Classifier: Development Status :: 4 - Beta
Classifier: Environment :: Web Environment
Classifier: Framework :: Django
Classifier: Intended Audience :: Developers
Classifier: License :: OSI Approved :: GNU General Public License v2 or later (GPLv2+)
Classifier: Operating System :: OS Independent
Classifier: Programming Language :: Python
Classifier: Topic :: Office/Business
